punsctl/__init__.py
punsctl/__main__.py
punsctl/exceptions.py
punsctl/main.py
punsctl/namespace.py
punsctl/rootspace.py
punsctl/sgetopt.py
punsctl/static.py
punsctl-0.2.6.dist-info/METADATA
punsctl-0.2.6.dist-info/WHEEL
punsctl-0.2.6.dist-info/entry_points.txt
punsctl-0.2.6.dist-info/licenses/LICENSE
punsctl-0.2.6.dist-info/RECORD
