Metadata-Version: 2.4
Name: punsctl
Version: 0.2.6
Summary: POSIX User's Namespace Control
Project-URL: Homepage, https://github.com/alekbuza/punsctl
Project-URL: Repository, https://github.com/alekbuza/punsctl
Project-URL: Issues, https://github.com/alekbuza/punsctl/issues
Project-URL: Changelog, https://github.com/alekbuza/punsctl/blob/main/CHANGELOG.md
Author-email: Aleksandar Buza <tech@aleksandarbuza.com>
License-File: LICENSE
Classifier: Environment :: Console
Classifier: License :: OSI Approved :: ISC License (ISCL)
Classifier: Operating System :: MacOS
Classifier: Operating System :: POSIX
Classifier: Operating System :: POSIX :: Linux
Classifier: Operating System :: Unix
Classifier: Programming Language :: Python :: 3
Classifier: Programming Language :: Python :: 3.9
Classifier: Programming Language :: Python :: 3.10
Classifier: Programming Language :: Python :: 3.12
Requires-Python: >=3.9
